hmdata/__init__.py
hmdata/totalcapture.py
hmdata/utils.py
hmdata-0.2.3.dist-info/LICENSE
hmdata-0.2.3.dist-info/METADATA
hmdata-0.2.3.dist-info/WHEEL
hmdata-0.2.3.dist-info/top_level.txt
hmdata-0.2.3.dist-info/RECORD
