Metadata-Version: 2.1
Name: hmdata
Version: 0.2.3
Summary: A package for human data
Home-page: https://github.com/YIN95/Human-Data-Utils
Author: Wenjie Yin
Author-email: yinwenjie159@hotmail.com
License: MIT license
Platform: UNKNOWN
Classifier: Programming Language :: Python :: 3
Classifier: License :: OSI Approved :: MIT License
Requires-Python: >=3.5
Requires-Dist: numba
Requires-Dist: numpy (>=1.16)
Requires-Dist: numpy-quaternion
Requires-Dist: pandas (>=0.24.2)
Requires-Dist: scipy (>=1.3.0)
Requires-Dist: torch (>=1.0.0)
Requires-Dist: torchvision (>=0.2.1)
Requires-Dist: tqdm
Requires-Dist: opencv-python
